git_reporter_ai/__init__.py
git_reporter_ai/ai/__init__.py
git_reporter_ai/ai/base.py
git_reporter_ai/ai/gemini_provider.py
git_reporter_ai/ai/openai_provider.py
git_reporter_ai/cli.py
git_reporter_ai/config/__init__.py
git_reporter_ai/config/manager.py
git_reporter_ai/git_analyzer.py
git_reporter_ai/models.py
git_reporter_ai/report_generator.py
git_reporter_ai-0.1.0.dist-info/WHEEL
git_reporter_ai-0.1.0.dist-info/entry_points.txt
git_reporter_ai-0.1.0.dist-info/METADATA
git_reporter_ai-0.1.0.dist-info/RECORD
