Metadata-Version: 2.3
Name: git-reporter-ai
Version: 0.1.0
Summary: AI-Powered Git commit history analyzer and report generator
Keywords: git,commit,history,report,ai,openai,gemini
Author: Xianpeng Shen
Author-email: Xianpeng Shen <xianpeng.shen@gmail.com>
Classifier: Development Status :: 3 - Alpha
Classifier: Intended Audience :: Developers
Classifier: License :: OSI Approved :: MIT License
Classifier: Programming Language :: Python :: 3.10
Classifier: Programming Language :: Python :: 3.11
Classifier: Programming Language :: Python :: 3.12
Classifier: Programming Language :: Python :: 3.13
Classifier: Programming Language :: Python :: 3.14
Classifier: Topic :: Software Development :: Version Control :: Git
Requires-Dist: gitpython>=3.1.43
Requires-Dist: pydantic>=2.10.0
Requires-Dist: pydantic-ai>=0.0.15
Requires-Dist: openai>=1.58.0
Requires-Dist: google-generativeai>=0.8.0
Requires-Dist: click>=8.1.7
Requires-Dist: python-dateutil>=2.9.0
Requires-Dist: pyyaml>=6.0.0
Requires-Dist: rich>=13.9.0
Requires-Dist: pytest>=8.3.0 ; extra == 'dev'
Requires-Dist: pytest-cov>=6.0.0 ; extra == 'dev'
Requires-Dist: ruff>=0.8.0 ; extra == 'dev'
Requires-Dist: mkdocs>=1.6.0 ; extra == 'docs'
Requires-Dist: mkdocs-material>=9.5.0 ; extra == 'docs'
Requires-Dist: mkdocs-git-revision-date-localized-plugin>=1.2.0 ; extra == 'docs'
Requires-Python: >=3.10
Project-URL: Documentation, https://shenxianpeng.github.io/git-reporter/
Project-URL: Homepage, https://github.com/shenxianpeng/git-reporter
Project-URL: Issues, https://github.com/shenxianpeng/git-reporter/issues
Project-URL: Repository, https://github.com/shenxianpeng/git-reporter
Provides-Extra: dev
Provides-Extra: docs
